odoo/addons/l10n_th_tax_report/README.rst
odoo/addons/l10n_th_tax_report/__init__.py
odoo/addons/l10n_th_tax_report/__manifest__.py
odoo/addons/l10n_th_tax_report/data/paper_format.xml
odoo/addons/l10n_th_tax_report/data/report_data.xml
odoo/addons/l10n_th_tax_report/i18n/l10n_th_tax_report.pot
odoo/addons/l10n_th_tax_report/i18n/th.po
odoo/addons/l10n_th_tax_report/readme/CONTRIBUTORS.rst
odoo/addons/l10n_th_tax_report/readme/DESCRIPTION.rst
odoo/addons/l10n_th_tax_report/readme/USAGE.rst
odoo/addons/l10n_th_tax_report/reports/__init__.py
odoo/addons/l10n_th_tax_report/reports/tax_report.py
odoo/addons/l10n_th_tax_report/reports/tax_report.xml
odoo/addons/l10n_th_tax_report/reports/tax_report_xlsx.py
odoo/addons/l10n_th_tax_report/security/ir.model.access.csv
odoo/addons/l10n_th_tax_report/static/description/icon.png
odoo/addons/l10n_th_tax_report/static/description/index.html
odoo/addons/l10n_th_tax_report/static/src/css/report.css
odoo/addons/l10n_th_tax_report/static/src/js/l10n_th_tax_report_backend.js
odoo/addons/l10n_th_tax_report/tests/__init__.py
odoo/addons/l10n_th_tax_report/tests/test_tax_report.py
odoo/addons/l10n_th_tax_report/wizard/__init__.py
odoo/addons/l10n_th_tax_report/wizard/tax_report_wizard.py
odoo/addons/l10n_th_tax_report/wizard/tax_report_wizard_view.xml
odoo14_addon_l10n_th_tax_report-14.0.1.0.1.dev6.dist-info/METADATA
odoo14_addon_l10n_th_tax_report-14.0.1.0.1.dev6.dist-info/WHEEL
odoo14_addon_l10n_th_tax_report-14.0.1.0.1.dev6.dist-info/top_level.txt
odoo14_addon_l10n_th_tax_report-14.0.1.0.1.dev6.dist-info/RECORD
