Metadata-Version: 2.1
Name: odoo14-addon-l10n-th-tax-report
Version: 14.0.1.0.1.dev6
Summary: Thailand Localization - TAX Reports
Home-page: https://github.com/OCA/l10n-thailand
Author: Ecosoft, Odoo Community Association (OCA)
Author-email: support@odoo-community.org
License: AGPL-3
Platform: UNKNOWN
Classifier: Programming Language :: Python
Classifier: Framework :: Odoo
Classifier: Framework :: Odoo :: 14.0
Classifier: License :: OSI Approved :: GNU Affero General Public License v3
Requires-Python: >=3.6
Requires-Dist: odoo14-addon-date-range
Requires-Dist: odoo14-addon-l10n-th-partner
Requires-Dist: odoo14-addon-l10n-th-tax-invoice
Requires-Dist: odoo14-addon-report-xlsx-helper
Requires-Dist: odoo <14.1dev,>=14.0a
